telegram_bot_logger/__init__.py
telegram_bot_logger/api_server.py
telegram_bot_logger/exceptions.py
telegram_bot_logger/formatters.py
telegram_bot_logger/handlers.py
telegram_bot_logger/utils.py
telegram_bot_logger-0.0.4.post0.dist-info/METADATA
telegram_bot_logger-0.0.4.post0.dist-info/WHEEL
telegram_bot_logger-0.0.4.post0.dist-info/top_level.txt
telegram_bot_logger-0.0.4.post0.dist-info/RECORD
