Metadata-Version: 2.2
Name: telegram_bot_logger
Version: 0.0.4.post0
Summary: It is a library that allows you to send logging logs to Telegram
Home-page: https://github.com/arynyklas/telegram_bot_logger
Author: Aryn Yklas
Author-email: arynyklas@gmail.com
Keywords: telegram,logger,logging,telegram_logger
Classifier: Programming Language :: Python
Classifier: Programming Language :: Python :: 3
Classifier: Programming Language :: Python :: 3.7
Requires-Python: >=3.7
Requires-Dist: httpx
Dynamic: author
Dynamic: author-email
Dynamic: classifier
Dynamic: description
Dynamic: description-content-type
Dynamic: home-page
Dynamic: keywords
Dynamic: requires-dist
Dynamic: requires-python
Dynamic: summary
